pyepgnotify/__init__.py
pyepgnotify/epgnotify.py
pyepgnotify/test.py
pyepgnotify-0.1.4.data/data/pyepgnotify/epgnotify.yml
pyepgnotify-0.1.4.dist-info/LICENSE
pyepgnotify-0.1.4.dist-info/METADATA
pyepgnotify-0.1.4.dist-info/WHEEL
pyepgnotify-0.1.4.dist-info/entry_points.txt
pyepgnotify-0.1.4.dist-info/top_level.txt
pyepgnotify-0.1.4.dist-info/RECORD
