Metadata-Version: 2.1
Name: pyepgnotify
Version: 0.1.4
Summary: Reads EPG data from VDR and sends user notification mails when desired programs are found
Home-page: https://github.com/Aikhjarto/pyepgnotify.git
Author: Thomas Wagner
Author-email: wagner-thomas@gmx.at
License: GPLv3
Download-URL: https://github.com/Aikhjarto/pyepgnotify/archive/v0.1.4.tar.gz
Keywords: VDR,EPG,mail,notification
Platform: UNKNOWN
Classifier: Development Status :: 3 - Alpha
Classifier: Programming Language :: Python :: 3
Requires-Python: >=3.5
Requires-Dist: pyyaml
